aroay_pyppeteer/__init__.py
aroay_pyppeteer/__version__.py
aroay_pyppeteer/downloadermiddlewares.py
aroay_pyppeteer/pretend.py
aroay_pyppeteer/request.py
aroay_pyppeteer/settings.py
aroay_pyppeteer-1.4.dist-info/LICENSE
aroay_pyppeteer-1.4.dist-info/METADATA
aroay_pyppeteer-1.4.dist-info/WHEEL
aroay_pyppeteer-1.4.dist-info/top_level.txt
aroay_pyppeteer-1.4.dist-info/RECORD
