Metadata-Version: 2.1
Name: aroay-pyppeteer
Version: 1.4
Summary: scrapy的一个下载中间件，无缝对接pyppeteer
Home-page: https://github.com/hwpchn/ScapyPyppeteer.git
Author: hwpchn
Author-email: 13692839895@163.com
License: UNKNOWN
Platform: UNKNOWN
Classifier: Programming Language :: Python :: 3
Classifier: License :: OSI Approved :: MIT License
Requires-Dist: scrapy (>=2.0.0)
Requires-Dist: pyppeteer (>=0.2.2)
